pyjson2dataclass/__init__.py
pyjson2dataclass/__main__.py
pyjson2dataclass/json2dataclass_test.py
pyjson2dataclass/utils.py
pyjson2dataclass-1.4.4.dist-info/METADATA
pyjson2dataclass-1.4.4.dist-info/WHEEL
pyjson2dataclass-1.4.4.dist-info/entry_points.txt
pyjson2dataclass-1.4.4.dist-info/top_level.txt
pyjson2dataclass-1.4.4.dist-info/RECORD
