Metadata-Version: 2.1
Name: pyjson2dataclass
Version: 1.4.4
Summary: Parse json to dataclass
Author: yinpeach
Project-URL: Homepage, https://github.com/verssionhack
Project-URL: Documentation, https://github.com/verssionhack/pyjson2dataclass/README.md
Project-URL: Repository, https://github.com/verssionhack/pyjson2dataclass.git
Keywords: dataclass,json,yinpeach
Requires-Python: >=3.9
